gevt/Mon_raid.gev
gevt/RTA2021.gev
gevt/VERSION
gevt/__init__.py
gevt/custom_parameter_tree.py
gevt/gevt.py
gevt/tasks.html
gevt/examples/RTA2018.gev
gevt/examples/__init__.py
gevt/examples/populate_table.py
gevt/examples/signaleurs.geojson
gevt/examples/tasks.csv
gevt/examples/volunteers.csv
gevt-0.1.16.dist-info/LICENSE
gevt-0.1.16.dist-info/METADATA
gevt-0.1.16.dist-info/WHEEL
gevt-0.1.16.dist-info/entry_points.txt
gevt-0.1.16.dist-info/top_level.txt
gevt-0.1.16.dist-info/RECORD
