Metadata-Version: 2.1
Name: gevt
Version: 0.1.16
Summary: Gestionnaire de Volontaires et de Tâches
Home-page: http://gevt.readthedocs.io
Author: Sébastien Weber
Author-email: sebastien.weber@cemes.fr
License: MIT
Platform: UNKNOWN
Classifier: Programming Language :: Python :: 3
Classifier: Development Status :: 5 - Production/Stable
Classifier: Environment :: Other Environment
Classifier: Intended Audience :: Science/Research
Classifier: Topic :: Scientific/Engineering :: Human Machine Interfaces
Classifier: Topic :: Scientific/Engineering :: Visualization
Classifier: License :: CeCILL-B Free Software License Agreement (CECILL-B)
Classifier: Operating System :: OS Independent
Classifier: Topic :: Software Development :: Libraries :: Python Modules
Classifier: Topic :: Software Development :: User Interfaces
Requires-Python: <3.9,>=3.7
License-File: LICENSE
Requires-Dist: pymodaq
